{"expires":"2026-07-01T12:42:17.0482958Z","files":[{"name":"BENZ-C6-VCI-V1.0.1.24-2026-0202.rar","url":"https://8d2cf9429e3c19524a14a659e5a07183.r2.cloudflarestorage.com/m-auto-software/Daimler/BENZ-C6-VCI-V1.0.1.24-2026-0202.rar?X-Amz-Algorithm=AWS4-HMAC-SHA256\u0026X-Amz-Credential=86893aa7e8a2ddb37580f2a7a8d9df83%2F20260701%2Fus-east-1%2Fs3%2Faws4_request\u0026X-Amz-Date=20260701T104217Z\u0026X-Amz-Expires=7200\u0026X-Amz-SignedHeaders=host\u0026x-id=GetObject\u0026X-Amz-Signature=cdf4d3d89a94f4c51405bf996ab780776cd55187b3b9cfe331952945369f3e89","size":10248059},{"name":"Certificates/Certificate 2026.08.26.exe","url":"https://8d2cf9429e3c19524a14a659e5a07183.r2.cloudflarestorage.com/m-auto-software/Daimler/Certificates/Certificate%202026.08.26.exe?X-Amz-Algorithm=AWS4-HMAC-SHA256\u0026X-Amz-Credential=86893aa7e8a2ddb37580f2a7a8d9df83%2F20260701%2Fus-east-1%2Fs3%2Faws4_request\u0026X-Amz-Date=20260701T104217Z\u0026X-Amz-Expires=7200\u0026X-Amz-SignedHeaders=host\u0026x-id=GetObject\u0026X-Amz-Signature=c6315e89c897cab9c1c00ea5b3d78db523e81de136af87a9d6a9cd59fc7fb707","size":216903},{"name":"Certificates/Mercedes Zenzefi Solution V1.80.0.10.7z","url":"https://8d2cf9429e3c19524a14a659e5a07183.r2.cloudflarestorage.com/m-auto-software/Daimler/Certificates/Mercedes%20Zenzefi%20Solution%20V1.80.0.10.7z?X-Amz-Algorithm=AWS4-HMAC-SHA256\u0026X-Amz-Credential=86893aa7e8a2ddb37580f2a7a8d9df83%2F20260701%2Fus-east-1%2Fs3%2Faws4_request\u0026X-Amz-Date=20260701T104217Z\u0026X-Amz-Expires=7200\u0026X-Amz-SignedHeaders=host\u0026x-id=GetObject\u0026X-Amz-Signature=6948ee011e718fba6116d7563ec6d8dde0c52897ba1f91625e10b50177752f3f","size":249498800},{"name":"Coding tutorials full.exe","url":"https://8d2cf9429e3c19524a14a659e5a07183.r2.cloudflarestorage.com/m-auto-software/Daimler/Coding%20tutorials%20full.exe?X-Amz-Algorithm=AWS4-HMAC-SHA256\u0026X-Amz-Credential=86893aa7e8a2ddb37580f2a7a8d9df83%2F20260701%2Fus-east-1%2Fs3%2Faws4_request\u0026X-Amz-Date=20260701T104217Z\u0026X-Amz-Expires=7200\u0026X-Amz-SignedHeaders=host\u0026x-id=GetObject\u0026X-Amz-Signature=5debcd072d58e041357334a5b8352992b3eea33465732bec7aeeb3e1e81f29cf","size":4211159525},{"name":"Database/Databases.7z","url":"https://8d2cf9429e3c19524a14a659e5a07183.r2.cloudflarestorage.com/m-auto-software/Daimler/Database/Databases.7z?X-Amz-Algorithm=AWS4-HMAC-SHA256\u0026X-Amz-Credential=86893aa7e8a2ddb37580f2a7a8d9df83%2F20260701%2Fus-east-1%2Fs3%2Faws4_request\u0026X-Amz-Date=20260701T104217Z\u0026X-Amz-Expires=7200\u0026X-Amz-SignedHeaders=host\u0026x-id=GetObject\u0026X-Amz-Signature=bebfe5d2cafe95bbc99322f809981b6a7ca24974866bc1ec2cca4e8d65a2d87a","size":11214205279},{"name":"Database/DTS9 SecOC.exe","url":"https://8d2cf9429e3c19524a14a659e5a07183.r2.cloudflarestorage.com/m-auto-software/Daimler/Database/DTS9%20SecOC.exe?X-Amz-Algorithm=AWS4-HMAC-SHA256\u0026X-Amz-Credential=86893aa7e8a2ddb37580f2a7a8d9df83%2F20260701%2Fus-east-1%2Fs3%2Faws4_request\u0026X-Amz-Date=20260701T104217Z\u0026X-Amz-Expires=7200\u0026X-Amz-SignedHeaders=host\u0026x-id=GetObject\u0026X-Amz-Signature=2e97900c085da17a5f70777a54251c9f2ad3d4889145575a400e8285343d6059","size":2324256470},{"name":"DControl.exe","url":"https://8d2cf9429e3c19524a14a659e5a07183.r2.cloudflarestorage.com/m-auto-software/Daimler/DControl.exe?X-Amz-Algorithm=AWS4-HMAC-SHA256\u0026X-Amz-Credential=86893aa7e8a2ddb37580f2a7a8d9df83%2F20260701%2Fus-east-1%2Fs3%2Faws4_request\u0026X-Amz-Date=20260701T104217Z\u0026X-Amz-Expires=7200\u0026X-Amz-SignedHeaders=host\u0026x-id=GetObject\u0026X-Amz-Signature=64f25fa833b077d3c82eb84dd3ac58a06550e7a014abb0e890663541bcbaa2b9","size":668910},{"name":"EPC 2018-11/EPC_1118_1of1_b1.iso","url":"https://8d2cf9429e3c19524a14a659e5a07183.r2.cloudflarestorage.com/m-auto-software/Daimler/EPC%202018-11/EPC_1118_1of1_b1.iso?X-Amz-Algorithm=AWS4-HMAC-SHA256\u0026X-Amz-Credential=86893aa7e8a2ddb37580f2a7a8d9df83%2F20260701%2Fus-east-1%2Fs3%2Faws4_request\u0026X-Amz-Date=20260701T104217Z\u0026X-Amz-Expires=7200\u0026X-Amz-SignedHeaders=host\u0026x-id=GetObject\u0026X-Amz-Signature=3f972997fccbe54ac5d39106aaab0f1010fcdb0167b43a57c78fa5624a4e4552","size":5667424256},{"name":"EPC 2018-11/EPC_1118_1of4_a1.iso","url":"https://8d2cf9429e3c19524a14a659e5a07183.r2.cloudflarestorage.com/m-auto-software/Daimler/EPC%202018-11/EPC_1118_1of4_a1.iso?X-Amz-Algorithm=AWS4-HMAC-SHA256\u0026X-Amz-Credential=86893aa7e8a2ddb37580f2a7a8d9df83%2F20260701%2Fus-east-1%2Fs3%2Faws4_request\u0026X-Amz-Date=20260701T104218Z\u0026X-Amz-Expires=7200\u0026X-Amz-SignedHeaders=host\u0026x-id=GetObject\u0026X-Amz-Signature=2a5d83bb8b4c632e83304ff61d6f828432edf1789d178b02a22f080b01b52f1e","size":8017301504},{"name":"EPC 2018-11/EPC_1118_2of4_a2.iso","url":"https://8d2cf9429e3c19524a14a659e5a07183.r2.cloudflarestorage.com/m-auto-software/Daimler/EPC%202018-11/EPC_1118_2of4_a2.iso?X-Amz-Algorithm=AWS4-HMAC-SHA256\u0026X-Amz-Credential=86893aa7e8a2ddb37580f2a7a8d9df83%2F20260701%2Fus-east-1%2Fs3%2Faws4_request\u0026X-Amz-Date=20260701T104218Z\u0026X-Amz-Expires=7200\u0026X-Amz-SignedHeaders=host\u0026x-id=GetObject\u0026X-Amz-Signature=bc826787808c6890aa49aa68c3418e76aa6822ab43d9ac0e6fdc6d38c31935f9","size":7530717184},{"name":"EPC 2018-11/EPC_1118_3of4_a3.iso","url":"https://8d2cf9429e3c19524a14a659e5a07183.r2.cloudflarestorage.com/m-auto-software/Daimler/EPC%202018-11/EPC_1118_3of4_a3.iso?X-Amz-Algorithm=AWS4-HMAC-SHA256\u0026X-Amz-Credential=86893aa7e8a2ddb37580f2a7a8d9df83%2F20260701%2Fus-east-1%2Fs3%2Faws4_request\u0026X-Amz-Date=20260701T104218Z\u0026X-Amz-Expires=7200\u0026X-Amz-SignedHeaders=host\u0026x-id=GetObject\u0026X-Amz-Signature=ef57600b68326b6f2e294a03d5d3f01478215658b2d91c38c98cff4280eac9bd","size":7031332864},{"name":"EPC 2018-11/EPC_1118_4of4_a4.iso","url":"https://8d2cf9429e3c19524a14a659e5a07183.r2.cloudflarestorage.com/m-auto-software/Daimler/EPC%202018-11/EPC_1118_4of4_a4.iso?X-Amz-Algorithm=AWS4-HMAC-SHA256\u0026X-Amz-Credential=86893aa7e8a2ddb37580f2a7a8d9df83%2F20260701%2Fus-east-1%2Fs3%2Faws4_request\u0026X-Amz-Date=20260701T104218Z\u0026X-Amz-Expires=7200\u0026X-Amz-SignedHeaders=host\u0026x-id=GetObject\u0026X-Amz-Signature=ba3a96e768588eaedc10e7dd129a6e1d340858500c26bd482bf8c2403e490c8f","size":3821287424},{"name":"EPC 2018-11/EPC_112018_FULL.rar","url":"https://8d2cf9429e3c19524a14a659e5a07183.r2.cloudflarestorage.com/m-auto-software/Daimler/EPC%202018-11/EPC_112018_FULL.rar?X-Amz-Algorithm=AWS4-HMAC-SHA256\u0026X-Amz-Credential=86893aa7e8a2ddb37580f2a7a8d9df83%2F20260701%2Fus-east-1%2Fs3%2Faws4_request\u0026X-Amz-Date=20260701T104218Z\u0026X-Amz-Expires=7200\u0026X-Amz-SignedHeaders=host\u0026x-id=GetObject\u0026X-Amz-Signature=b77ff5b0e3ba910aa006e193d864e7aa6936b39c6ff8d8dc6f68ee1342db0346","size":154459},{"name":"EPC 2018-11/EWA.7z","url":"https://8d2cf9429e3c19524a14a659e5a07183.r2.cloudflarestorage.com/m-auto-software/Daimler/EPC%202018-11/EWA.7z?X-Amz-Algorithm=AWS4-HMAC-SHA256\u0026X-Amz-Credential=86893aa7e8a2ddb37580f2a7a8d9df83%2F20260701%2Fus-east-1%2Fs3%2Faws4_request\u0026X-Amz-Date=20260701T104218Z\u0026X-Amz-Expires=7200\u0026X-Amz-SignedHeaders=host\u0026x-id=GetObject\u0026X-Amz-Signature=66ad1204a1551624fadfd5893fbc17efdd045d963acbe86dda306a42002b24de","size":494901184},{"name":"fix/4.0.5.zip","url":"https://8d2cf9429e3c19524a14a659e5a07183.r2.cloudflarestorage.com/m-auto-software/Daimler/fix/4.0.5.zip?X-Amz-Algorithm=AWS4-HMAC-SHA256\u0026X-Amz-Credential=86893aa7e8a2ddb37580f2a7a8d9df83%2F20260701%2Fus-east-1%2Fs3%2Faws4_request\u0026X-Amz-Date=20260701T104218Z\u0026X-Amz-Expires=7200\u0026X-Amz-SignedHeaders=host\u0026x-id=GetObject\u0026X-Amz-Signature=ea85e23bb344820ce02e247b53857176d92d6529c279dc78c728515d4695b5f0","size":1700437358},{"name":"fix/FullFix for Xentry and Truck v9.1.1.exe","url":"https://8d2cf9429e3c19524a14a659e5a07183.r2.cloudflarestorage.com/m-auto-software/Daimler/fix/FullFix%20for%20Xentry%20and%20Truck%20v9.1.1.exe?X-Amz-Algorithm=AWS4-HMAC-SHA256\u0026X-Amz-Credential=86893aa7e8a2ddb37580f2a7a8d9df83%2F20260701%2Fus-east-1%2Fs3%2Faws4_request\u0026X-Amz-Date=20260701T104218Z\u0026X-Amz-Expires=7200\u0026X-Amz-SignedHeaders=host\u0026x-id=GetObject\u0026X-Amz-Signature=d87c2510130bf9947dcced8e14306d6dd5837d445d17b6d1608a9eb10f62a25a","size":3964057514},{"name":"fix/XENTRY.AIO.FULL.FIX_2023.09_R2-c0n.7z","url":"https://8d2cf9429e3c19524a14a659e5a07183.r2.cloudflarestorage.com/m-auto-software/Daimler/fix/XENTRY.AIO.FULL.FIX_2023.09_R2-c0n.7z?X-Amz-Algorithm=AWS4-HMAC-SHA256\u0026X-Amz-Credential=86893aa7e8a2ddb37580f2a7a8d9df83%2F20260701%2Fus-east-1%2Fs3%2Faws4_request\u0026X-Amz-Date=20260701T104218Z\u0026X-Amz-Expires=7200\u0026X-Amz-SignedHeaders=host\u0026x-id=GetObject\u0026X-Amz-Signature=372f6b16922da0c3449ee4ea211fe83d9d4c1d61814e1b6566e1b85963f200b6","size":231896386},{"name":"M-Auto-Launcher.zip","url":"https://8d2cf9429e3c19524a14a659e5a07183.r2.cloudflarestorage.com/m-auto-software/Daimler/M-Auto-Launcher.zip?X-Amz-Algorithm=AWS4-HMAC-SHA256\u0026X-Amz-Credential=86893aa7e8a2ddb37580f2a7a8d9df83%2F20260701%2Fus-east-1%2Fs3%2Faws4_request\u0026X-Amz-Date=20260701T104218Z\u0026X-Amz-Expires=7200\u0026X-Amz-SignedHeaders=host\u0026x-id=GetObject\u0026X-Amz-Signature=439f7f4bcc4781e22983a55f00eec18d2dabe47aa9f316e6a85996e581ef4f07","size":118458375},{"name":"MB ECU CLEAR v1.67.zip","url":"https://8d2cf9429e3c19524a14a659e5a07183.r2.cloudflarestorage.com/m-auto-software/Daimler/MB%20ECU%20CLEAR%20v1.67.zip?X-Amz-Algorithm=AWS4-HMAC-SHA256\u0026X-Amz-Credential=86893aa7e8a2ddb37580f2a7a8d9df83%2F20260701%2Fus-east-1%2Fs3%2Faws4_request\u0026X-Amz-Date=20260701T104218Z\u0026X-Amz-Expires=7200\u0026X-Amz-SignedHeaders=host\u0026x-id=GetObject\u0026X-Amz-Signature=0d6b8513886f34baec2b7033a7cda4a849412d430778cac275c1292db1bed20c","size":190353},{"name":"SDMEDIA.zip","url":"https://8d2cf9429e3c19524a14a659e5a07183.r2.cloudflarestorage.com/m-auto-software/Daimler/SDMEDIA.zip?X-Amz-Algorithm=AWS4-HMAC-SHA256\u0026X-Amz-Credential=86893aa7e8a2ddb37580f2a7a8d9df83%2F20260701%2Fus-east-1%2Fs3%2Faws4_request\u0026X-Amz-Date=20260701T104218Z\u0026X-Amz-Expires=7200\u0026X-Amz-SignedHeaders=host\u0026x-id=GetObject\u0026X-Amz-Signature=2d806cc99db79b9bf17c31c4e9d8e30941c7b8a979b16099884a1c8fa7aa43ce","size":10615512251},{"name":"Startfifinder 2024.7z","url":"https://8d2cf9429e3c19524a14a659e5a07183.r2.cloudflarestorage.com/m-auto-software/Daimler/Startfifinder%202024.7z?X-Amz-Algorithm=AWS4-HMAC-SHA256\u0026X-Amz-Credential=86893aa7e8a2ddb37580f2a7a8d9df83%2F20260701%2Fus-east-1%2Fs3%2Faws4_request\u0026X-Amz-Date=20260701T104218Z\u0026X-Amz-Expires=7200\u0026X-Amz-SignedHeaders=host\u0026x-id=GetObject\u0026X-Amz-Signature=c3ae1b5f3d0aac6592c574f1029e4f2267da9eb40db5b039feea27368b95f0a0","size":11131912544},{"name":"Tools/BlackList_Fix.exe","url":"https://8d2cf9429e3c19524a14a659e5a07183.r2.cloudflarestorage.com/m-auto-software/Daimler/Tools/BlackList_Fix.exe?X-Amz-Algorithm=AWS4-HMAC-SHA256\u0026X-Amz-Credential=86893aa7e8a2ddb37580f2a7a8d9df83%2F20260701%2Fus-east-1%2Fs3%2Faws4_request\u0026X-Amz-Date=20260701T104218Z\u0026X-Amz-Expires=7200\u0026X-Amz-SignedHeaders=host\u0026x-id=GetObject\u0026X-Amz-Signature=445586ae386049c41a811ebe12494b339130225fa37e5e241bc9905d1c6b0e83","size":2883183},{"name":"Tools/DAS.FDOK.Keygen_autogmt.com.exe","url":"https://8d2cf9429e3c19524a14a659e5a07183.r2.cloudflarestorage.com/m-auto-software/Daimler/Tools/DAS.FDOK.Keygen_autogmt.com.exe?X-Amz-Algorithm=AWS4-HMAC-SHA256\u0026X-Amz-Credential=86893aa7e8a2ddb37580f2a7a8d9df83%2F20260701%2Fus-east-1%2Fs3%2Faws4_request\u0026X-Amz-Date=20260701T104218Z\u0026X-Amz-Expires=7200\u0026X-Amz-SignedHeaders=host\u0026x-id=GetObject\u0026X-Amz-Signature=6331f4491fc3b748186f799099bbb93b924130d2b410ed6a4a7a374a35c5d8db","size":2051072},{"name":"Tools/XENTRY.Special.Functions.Keygen.v1.2_autogmt.com.exe","url":"https://8d2cf9429e3c19524a14a659e5a07183.r2.cloudflarestorage.com/m-auto-software/Daimler/Tools/XENTRY.Special.Functions.Keygen.v1.2_autogmt.com.exe?X-Amz-Algorithm=AWS4-HMAC-SHA256\u0026X-Amz-Credential=86893aa7e8a2ddb37580f2a7a8d9df83%2F20260701%2Fus-east-1%2Fs3%2Faws4_request\u0026X-Amz-Date=20260701T104218Z\u0026X-Amz-Expires=7200\u0026X-Amz-SignedHeaders=host\u0026x-id=GetObject\u0026X-Amz-Signature=77b68040118407795844082b845de476d57143a223c812de9fbb7a75767cd987","size":2136576},{"name":"tutorial beta.exe","url":"https://8d2cf9429e3c19524a14a659e5a07183.r2.cloudflarestorage.com/m-auto-software/Daimler/tutorial%20beta.exe?X-Amz-Algorithm=AWS4-HMAC-SHA256\u0026X-Amz-Credential=86893aa7e8a2ddb37580f2a7a8d9df83%2F20260701%2Fus-east-1%2Fs3%2Faws4_request\u0026X-Amz-Date=20260701T104218Z\u0026X-Amz-Expires=7200\u0026X-Amz-SignedHeaders=host\u0026x-id=GetObject\u0026X-Amz-Signature=9d82c9da3b14b0e47331815f45e03668c7f7a47f2a5039da87d3a5881bcffd3f","size":52063659},{"name":"VCX.7z","url":"https://8d2cf9429e3c19524a14a659e5a07183.r2.cloudflarestorage.com/m-auto-software/Daimler/VCX.7z?X-Amz-Algorithm=AWS4-HMAC-SHA256\u0026X-Amz-Credential=86893aa7e8a2ddb37580f2a7a8d9df83%2F20260701%2Fus-east-1%2Fs3%2Faws4_request\u0026X-Amz-Date=20260701T104219Z\u0026X-Amz-Expires=7200\u0026X-Amz-SignedHeaders=host\u0026x-id=GetObject\u0026X-Amz-Signature=132b2ec4e9fcd517acbce74a734638dd262762f0871e2a2e451cb95ccd38bc72","size":76561337},{"name":"Vediamo/vediamo 5 passthru.zip","url":"https://8d2cf9429e3c19524a14a659e5a07183.r2.cloudflarestorage.com/m-auto-software/Daimler/Vediamo/vediamo%205%20passthru.zip?X-Amz-Algorithm=AWS4-HMAC-SHA256\u0026X-Amz-Credential=86893aa7e8a2ddb37580f2a7a8d9df83%2F20260701%2Fus-east-1%2Fs3%2Faws4_request\u0026X-Amz-Date=20260701T104219Z\u0026X-Amz-Expires=7200\u0026X-Amz-SignedHeaders=host\u0026x-id=GetObject\u0026X-Amz-Signature=f76f48a2ad1139f4aff63b74a66c3ac0d234c9251501c844b47d06df9d28ec38","size":640623},{"name":"Vediamo/Vediamo J2534.exe","url":"https://8d2cf9429e3c19524a14a659e5a07183.r2.cloudflarestorage.com/m-auto-software/Daimler/Vediamo/Vediamo%20J2534.exe?X-Amz-Algorithm=AWS4-HMAC-SHA256\u0026X-Amz-Credential=86893aa7e8a2ddb37580f2a7a8d9df83%2F20260701%2Fus-east-1%2Fs3%2Faws4_request\u0026X-Amz-Date=20260701T104219Z\u0026X-Amz-Expires=7200\u0026X-Amz-SignedHeaders=host\u0026x-id=GetObject\u0026X-Amz-Signature=8964962a1c7ff3fbff71709e003c09a39b299eb88d0586fee894b5fffd503c35","size":151040},{"name":"Vin decoder.7z","url":"https://8d2cf9429e3c19524a14a659e5a07183.r2.cloudflarestorage.com/m-auto-software/Daimler/Vin%20decoder.7z?X-Amz-Algorithm=AWS4-HMAC-SHA256\u0026X-Amz-Credential=86893aa7e8a2ddb37580f2a7a8d9df83%2F20260701%2Fus-east-1%2Fs3%2Faws4_request\u0026X-Amz-Date=20260701T104219Z\u0026X-Amz-Expires=7200\u0026X-Amz-SignedHeaders=host\u0026x-id=GetObject\u0026X-Amz-Signature=259a07c299a04f3674cc2389d26551268082e533a6f417990694c61464e7a251","size":12905970},{"name":"wis2021.rar","url":"https://8d2cf9429e3c19524a14a659e5a07183.r2.cloudflarestorage.com/m-auto-software/Daimler/wis2021.rar?X-Amz-Algorithm=AWS4-HMAC-SHA256\u0026X-Amz-Credential=86893aa7e8a2ddb37580f2a7a8d9df83%2F20260701%2Fus-east-1%2Fs3%2Faws4_request\u0026X-Amz-Date=20260701T104219Z\u0026X-Amz-Expires=7200\u0026X-Amz-SignedHeaders=host\u0026x-id=GetObject\u0026X-Amz-Signature=b34041ecce5af2011fc085604562dc8ba268613362b60db0f45adea038b2caf1","size":15506091246},{"name":"XENTRY/DT 04-26.7z","url":"https://8d2cf9429e3c19524a14a659e5a07183.r2.cloudflarestorage.com/m-auto-software/Daimler/XENTRY/DT%2004-26.7z?X-Amz-Algorithm=AWS4-HMAC-SHA256\u0026X-Amz-Credential=86893aa7e8a2ddb37580f2a7a8d9df83%2F20260701%2Fus-east-1%2Fs3%2Faws4_request\u0026X-Amz-Date=20260701T104219Z\u0026X-Amz-Expires=7200\u0026X-Amz-SignedHeaders=host\u0026x-id=GetObject\u0026X-Amz-Signature=d21c5a9ef961a8605f2b5e20f71dd1f45c9b170163d06f4287e9c28bbab0d479","size":11061920260},{"name":"XENTRY/XDOS 06-2026.exe","url":"https://8d2cf9429e3c19524a14a659e5a07183.r2.cloudflarestorage.com/m-auto-software/Daimler/XENTRY/XDOS%2006-2026.exe?X-Amz-Algorithm=AWS4-HMAC-SHA256\u0026X-Amz-Credential=86893aa7e8a2ddb37580f2a7a8d9df83%2F20260701%2Fus-east-1%2Fs3%2Faws4_request\u0026X-Amz-Date=20260701T104219Z\u0026X-Amz-Expires=7200\u0026X-Amz-SignedHeaders=host\u0026x-id=GetObject\u0026X-Amz-Signature=21dfd89d4f57a42a083a88428c2a31786286562eed645c1b368bc0432ce1e3e3","size":17777467091},{"name":"XENTRY/Xentry XPT 2605.exe","url":"https://8d2cf9429e3c19524a14a659e5a07183.r2.cloudflarestorage.com/m-auto-software/Daimler/XENTRY/Xentry%20XPT%202605.exe?X-Amz-Algorithm=AWS4-HMAC-SHA256\u0026X-Amz-Credential=86893aa7e8a2ddb37580f2a7a8d9df83%2F20260701%2Fus-east-1%2Fs3%2Faws4_request\u0026X-Amz-Date=20260701T104219Z\u0026X-Amz-Expires=7200\u0026X-Amz-SignedHeaders=host\u0026x-id=GetObject\u0026X-Amz-Signature=85857b68b0a299cbab0f6c0e35c092833a5792243d053ff3d7124bdb5ba9b568","size":17556775747},{"name":"XENTRY/XENTRY.Diagnostics.OpenShell.v03.2026_26.3.4.rar","url":"https://8d2cf9429e3c19524a14a659e5a07183.r2.cloudflarestorage.com/m-auto-software/Daimler/XENTRY/XENTRY.Diagnostics.OpenShell.v03.2026_26.3.4.rar?X-Amz-Algorithm=AWS4-HMAC-SHA256\u0026X-Amz-Credential=86893aa7e8a2ddb37580f2a7a8d9df83%2F20260701%2Fus-east-1%2Fs3%2Faws4_request\u0026X-Amz-Date=20260701T104219Z\u0026X-Amz-Expires=7200\u0026X-Amz-SignedHeaders=host\u0026x-id=GetObject\u0026X-Amz-Signature=fbee81b660d8ca1284ea0c57f2ac69bedef4f55d11aa4fc2c1795811f5192b65","size":17882685998}]}