{
    "expires":  "2026-04-28T15:40:30.5370102Z",
    "files":  [
                  {
                      "name":  "202608.7z",
                      "url":  "https://8d2cf9429e3c19524a14a659e5a07183.r2.cloudflarestorage.com/m-auto-software/Daimler/Pack/Installer/202608.7z?X-Amz-Algorithm=AWS4-HMAC-SHA256\u0026X-Amz-Credential=59cb46144927b03a7dc575be0b734ff4%2F20260428%2Fus-east-1%2Fs3%2Faws4_request\u0026X-Amz-Date=20260428T134031Z\u0026X-Amz-Expires=7200\u0026X-Amz-SignedHeaders=host\u0026x-id=GetObject\u0026X-Amz-Signature=0fa1aeef0da32cf6744a652164365125be17e3eeff02985dcec5bbb67ffe2f96"
                  },
                  {
                      "name":  "7z2501-x64.exe",
                      "url":  "https://8d2cf9429e3c19524a14a659e5a07183.r2.cloudflarestorage.com/m-auto-software/Daimler/Pack/Installer/7z2501-x64.exe?X-Amz-Algorithm=AWS4-HMAC-SHA256\u0026X-Amz-Credential=59cb46144927b03a7dc575be0b734ff4%2F20260428%2Fus-east-1%2Fs3%2Faws4_request\u0026X-Amz-Date=20260428T134031Z\u0026X-Amz-Expires=7200\u0026X-Amz-SignedHeaders=host\u0026x-id=GetObject\u0026X-Amz-Signature=6b8897d26463cb44f135d0b213acf466e319beec2039f1a77b156e2e4e4dd190"
                  },
                  {
                      "name":  "Coding tutorials full.7z",
                      "url":  "https://8d2cf9429e3c19524a14a659e5a07183.r2.cloudflarestorage.com/m-auto-software/Daimler/Pack/Installer/Coding%20tutorials%20full.7z?X-Amz-Algorithm=AWS4-HMAC-SHA256\u0026X-Amz-Credential=59cb46144927b03a7dc575be0b734ff4%2F20260428%2Fus-east-1%2Fs3%2Faws4_request\u0026X-Amz-Date=20260428T134031Z\u0026X-Amz-Expires=7200\u0026X-Amz-SignedHeaders=host\u0026x-id=GetObject\u0026X-Amz-Signature=aa7049f4271f2576cfd446ac76e300c32fd7672a7706ecafcf5451a5089debc1"
                  },
                  {
                      "name":  "Databases.7z",
                      "url":  "https://8d2cf9429e3c19524a14a659e5a07183.r2.cloudflarestorage.com/m-auto-software/Daimler/Pack/Installer/Databases.7z?X-Amz-Algorithm=AWS4-HMAC-SHA256\u0026X-Amz-Credential=59cb46144927b03a7dc575be0b734ff4%2F20260428%2Fus-east-1%2Fs3%2Faws4_request\u0026X-Amz-Date=20260428T134031Z\u0026X-Amz-Expires=7200\u0026X-Amz-SignedHeaders=host\u0026x-id=GetObject\u0026X-Amz-Signature=740f73b430e646dcf2a41771e87820e357678ca6853c9c304a13d29744c26817"
                  },
                  {
                      "name":  "DT 04-26.7z",
                      "url":  "https://8d2cf9429e3c19524a14a659e5a07183.r2.cloudflarestorage.com/m-auto-software/Daimler/Pack/Installer/DT%2004-26.7z?X-Amz-Algorithm=AWS4-HMAC-SHA256\u0026X-Amz-Credential=59cb46144927b03a7dc575be0b734ff4%2F20260428%2Fus-east-1%2Fs3%2Faws4_request\u0026X-Amz-Date=20260428T134031Z\u0026X-Amz-Expires=7200\u0026X-Amz-SignedHeaders=host\u0026x-id=GetObject\u0026X-Amz-Signature=93832690ce344372d2fbc4e881d16c698acc44c3955e50e3989d8f43cfe98a58"
                  },
                  {
                      "name":  "EPC 2018-11/EPC_1118_1of1_b1.iso",
                      "url":  "https://8d2cf9429e3c19524a14a659e5a07183.r2.cloudflarestorage.com/m-auto-software/Daimler/Pack/Installer/EPC%202018-11/EPC_1118_1of1_b1.iso?X-Amz-Algorithm=AWS4-HMAC-SHA256\u0026X-Amz-Credential=59cb46144927b03a7dc575be0b734ff4%2F20260428%2Fus-east-1%2Fs3%2Faws4_request\u0026X-Amz-Date=20260428T134031Z\u0026X-Amz-Expires=7200\u0026X-Amz-SignedHeaders=host\u0026x-id=GetObject\u0026X-Amz-Signature=13c5f1bafd73ac1a1e27833b33beac311eab5de024cc71ca718af88aaaf54d77"
                  },
                  {
                      "name":  "EPC 2018-11/EPC_1118_1of4_a1.iso",
                      "url":  "https://8d2cf9429e3c19524a14a659e5a07183.r2.cloudflarestorage.com/m-auto-software/Daimler/Pack/Installer/EPC%202018-11/EPC_1118_1of4_a1.iso?X-Amz-Algorithm=AWS4-HMAC-SHA256\u0026X-Amz-Credential=59cb46144927b03a7dc575be0b734ff4%2F20260428%2Fus-east-1%2Fs3%2Faws4_request\u0026X-Amz-Date=20260428T134031Z\u0026X-Amz-Expires=7200\u0026X-Amz-SignedHeaders=host\u0026x-id=GetObject\u0026X-Amz-Signature=3638017dad8f13a4adeb61566fbca85602094f211c925497e7a277bbf81d8e56"
                  },
                  {
                      "name":  "EPC 2018-11/EPC_1118_2of4_a2.iso",
                      "url":  "https://8d2cf9429e3c19524a14a659e5a07183.r2.cloudflarestorage.com/m-auto-software/Daimler/Pack/Installer/EPC%202018-11/EPC_1118_2of4_a2.iso?X-Amz-Algorithm=AWS4-HMAC-SHA256\u0026X-Amz-Credential=59cb46144927b03a7dc575be0b734ff4%2F20260428%2Fus-east-1%2Fs3%2Faws4_request\u0026X-Amz-Date=20260428T134031Z\u0026X-Amz-Expires=7200\u0026X-Amz-SignedHeaders=host\u0026x-id=GetObject\u0026X-Amz-Signature=74a3e395b344769968736dbf0e6a03872fa4fc22c8255e523fffe4199bf63679"
                  },
                  {
                      "name":  "EPC 2018-11/EPC_1118_3of4_a3.iso",
                      "url":  "https://8d2cf9429e3c19524a14a659e5a07183.r2.cloudflarestorage.com/m-auto-software/Daimler/Pack/Installer/EPC%202018-11/EPC_1118_3of4_a3.iso?X-Amz-Algorithm=AWS4-HMAC-SHA256\u0026X-Amz-Credential=59cb46144927b03a7dc575be0b734ff4%2F20260428%2Fus-east-1%2Fs3%2Faws4_request\u0026X-Amz-Date=20260428T134031Z\u0026X-Amz-Expires=7200\u0026X-Amz-SignedHeaders=host\u0026x-id=GetObject\u0026X-Amz-Signature=5b5d2f3eb1a7c7c1f6bfc7b6bf2246ac8441886677351be74bcba4e85b6b5296"
                  },
                  {
                      "name":  "EPC 2018-11/EPC_1118_4of4_a4.iso",
                      "url":  "https://8d2cf9429e3c19524a14a659e5a07183.r2.cloudflarestorage.com/m-auto-software/Daimler/Pack/Installer/EPC%202018-11/EPC_1118_4of4_a4.iso?X-Amz-Algorithm=AWS4-HMAC-SHA256\u0026X-Amz-Credential=59cb46144927b03a7dc575be0b734ff4%2F20260428%2Fus-east-1%2Fs3%2Faws4_request\u0026X-Amz-Date=20260428T134031Z\u0026X-Amz-Expires=7200\u0026X-Amz-SignedHeaders=host\u0026x-id=GetObject\u0026X-Amz-Signature=00e18d0617d55c1c88096e517f30898f92d06d089026dc1a100a14f7cb5f7aa9"
                  },
                  {
                      "name":  "EPC 2018-11/EPC_112018_FULL.rar",
                      "url":  "https://8d2cf9429e3c19524a14a659e5a07183.r2.cloudflarestorage.com/m-auto-software/Daimler/Pack/Installer/EPC%202018-11/EPC_112018_FULL.rar?X-Amz-Algorithm=AWS4-HMAC-SHA256\u0026X-Amz-Credential=59cb46144927b03a7dc575be0b734ff4%2F20260428%2Fus-east-1%2Fs3%2Faws4_request\u0026X-Amz-Date=20260428T134031Z\u0026X-Amz-Expires=7200\u0026X-Amz-SignedHeaders=host\u0026x-id=GetObject\u0026X-Amz-Signature=2a573c51f63cde81bf367b8a1913cffea31fbc7d179b820662b3f48fb8ad7504"
                  },
                  {
                      "name":  "EWA.7z",
                      "url":  "https://8d2cf9429e3c19524a14a659e5a07183.r2.cloudflarestorage.com/m-auto-software/Daimler/Pack/Installer/EWA.7z?X-Amz-Algorithm=AWS4-HMAC-SHA256\u0026X-Amz-Credential=59cb46144927b03a7dc575be0b734ff4%2F20260428%2Fus-east-1%2Fs3%2Faws4_request\u0026X-Amz-Date=20260428T134031Z\u0026X-Amz-Expires=7200\u0026X-Amz-SignedHeaders=host\u0026x-id=GetObject\u0026X-Amz-Signature=967bad7e8477d456c9f2db21a8b0dcff9b5f155494be588a39526d7bff2c0af8"
                  },
                  {
                      "name":  "FullFix By Samik v4.9.3.exe",
                      "url":  "https://8d2cf9429e3c19524a14a659e5a07183.r2.cloudflarestorage.com/m-auto-software/Daimler/Pack/Installer/FullFix%20By%20Samik%20v4.9.3.exe?X-Amz-Algorithm=AWS4-HMAC-SHA256\u0026X-Amz-Credential=59cb46144927b03a7dc575be0b734ff4%2F20260428%2Fus-east-1%2Fs3%2Faws4_request\u0026X-Amz-Date=20260428T134031Z\u0026X-Amz-Expires=7200\u0026X-Amz-SignedHeaders=host\u0026x-id=GetObject\u0026X-Amz-Signature=85f324af1200ef15cb8cbed13659399e8de9b40948f21e2ccb95a4503bf9fc7c"
                  },
                  {
                      "name":  "FullFix for Xentry and Truck v9.0.8.exe",
                      "url":  "https://8d2cf9429e3c19524a14a659e5a07183.r2.cloudflarestorage.com/m-auto-software/Daimler/Pack/Installer/FullFix%20for%20Xentry%20and%20Truck%20v9.0.8.exe?X-Amz-Algorithm=AWS4-HMAC-SHA256\u0026X-Amz-Credential=59cb46144927b03a7dc575be0b734ff4%2F20260428%2Fus-east-1%2Fs3%2Faws4_request\u0026X-Amz-Date=20260428T134032Z\u0026X-Amz-Expires=7200\u0026X-Amz-SignedHeaders=host\u0026x-id=GetObject\u0026X-Amz-Signature=ebe6b78670c43abc43727c11778dc3506e12db815911f69ae9a036cce24a6404"
                  },
                  {
                      "name":  "MB ECU CLEAR v1.67.zip",
                      "url":  "https://8d2cf9429e3c19524a14a659e5a07183.r2.cloudflarestorage.com/m-auto-software/Daimler/Pack/Installer/MB%20ECU%20CLEAR%20v1.67.zip?X-Amz-Algorithm=AWS4-HMAC-SHA256\u0026X-Amz-Credential=59cb46144927b03a7dc575be0b734ff4%2F20260428%2Fus-east-1%2Fs3%2Faws4_request\u0026X-Amz-Date=20260428T134032Z\u0026X-Amz-Expires=7200\u0026X-Amz-SignedHeaders=host\u0026x-id=GetObject\u0026X-Amz-Signature=55679d2d154e127094fc783ff931bc2e6f7cf42d2e8b8e810d9c3a869dd160ec"
                  },
                  {
                      "name":  "MB_VIN v3.0.3 D-PDU.rar",
                      "url":  "https://8d2cf9429e3c19524a14a659e5a07183.r2.cloudflarestorage.com/m-auto-software/Daimler/Pack/Installer/MB_VIN%20v3.0.3%20D-PDU.rar?X-Amz-Algorithm=AWS4-HMAC-SHA256\u0026X-Amz-Credential=59cb46144927b03a7dc575be0b734ff4%2F20260428%2Fus-east-1%2Fs3%2Faws4_request\u0026X-Amz-Date=20260428T134032Z\u0026X-Amz-Expires=7200\u0026X-Amz-SignedHeaders=host\u0026x-id=GetObject\u0026X-Amz-Signature=9295b0e751e960ec7052dd7ec0cbd90e528948c64cc21c8b1fefd720d89df4e0"
                  },
                  {
                      "name":  "MB_VIN v3.0.3 J2534.rar",
                      "url":  "https://8d2cf9429e3c19524a14a659e5a07183.r2.cloudflarestorage.com/m-auto-software/Daimler/Pack/Installer/MB_VIN%20v3.0.3%20J2534.rar?X-Amz-Algorithm=AWS4-HMAC-SHA256\u0026X-Amz-Credential=59cb46144927b03a7dc575be0b734ff4%2F20260428%2Fus-east-1%2Fs3%2Faws4_request\u0026X-Amz-Date=20260428T134032Z\u0026X-Amz-Expires=7200\u0026X-Amz-SignedHeaders=host\u0026x-id=GetObject\u0026X-Amz-Signature=150e588139ec54f97148c3f0d2ba51d1b5c74f67f6dc19eb750d4f9267a70da5"
                  },
                  {
                      "name":  "Mercedes Zenzefi Solution V1.80.0.10.7z",
                      "url":  "https://8d2cf9429e3c19524a14a659e5a07183.r2.cloudflarestorage.com/m-auto-software/Daimler/Pack/Installer/Mercedes%20Zenzefi%20Solution%20V1.80.0.10.7z?X-Amz-Algorithm=AWS4-HMAC-SHA256\u0026X-Amz-Credential=59cb46144927b03a7dc575be0b734ff4%2F20260428%2Fus-east-1%2Fs3%2Faws4_request\u0026X-Amz-Date=20260428T134032Z\u0026X-Amz-Expires=7200\u0026X-Amz-SignedHeaders=host\u0026x-id=GetObject\u0026X-Amz-Signature=31ffe68a354adeaeb8b0a830bdb1a61c708736b31e3e96ad68dda40d604616ce"
                  },
                  {
                      "name":  "OfflineAccountTool.exe",
                      "url":  "https://8d2cf9429e3c19524a14a659e5a07183.r2.cloudflarestorage.com/m-auto-software/Daimler/Pack/Installer/OfflineAccountTool.exe?X-Amz-Algorithm=AWS4-HMAC-SHA256\u0026X-Amz-Credential=59cb46144927b03a7dc575be0b734ff4%2F20260428%2Fus-east-1%2Fs3%2Faws4_request\u0026X-Amz-Date=20260428T134032Z\u0026X-Amz-Expires=7200\u0026X-Amz-SignedHeaders=host\u0026x-id=GetObject\u0026X-Amz-Signature=4ce32379dab386f9002268521262347a33a7ca384efb00597c9ac1e80448022a"
                  },
                  {
                      "name":  "SDMEDIA.zip",
                      "url":  "https://8d2cf9429e3c19524a14a659e5a07183.r2.cloudflarestorage.com/m-auto-software/Daimler/Pack/Installer/SDMEDIA.zip?X-Amz-Algorithm=AWS4-HMAC-SHA256\u0026X-Amz-Credential=59cb46144927b03a7dc575be0b734ff4%2F20260428%2Fus-east-1%2Fs3%2Faws4_request\u0026X-Amz-Date=20260428T134032Z\u0026X-Amz-Expires=7200\u0026X-Amz-SignedHeaders=host\u0026x-id=GetObject\u0026X-Amz-Signature=e9e635683a9a02c2e08e4158650a736bebe038f512b3b98b635822d813785b4d"
                  },
                  {
                      "name":  "sordum.rar",
                      "url":  "https://8d2cf9429e3c19524a14a659e5a07183.r2.cloudflarestorage.com/m-auto-software/Daimler/Pack/Installer/sordum.rar?X-Amz-Algorithm=AWS4-HMAC-SHA256\u0026X-Amz-Credential=59cb46144927b03a7dc575be0b734ff4%2F20260428%2Fus-east-1%2Fs3%2Faws4_request\u0026X-Amz-Date=20260428T134032Z\u0026X-Amz-Expires=7200\u0026X-Amz-SignedHeaders=host\u0026x-id=GetObject\u0026X-Amz-Signature=a166851509ec5df885e1dc630a47ff386166643e13415377be2001f10192b498"
                  },
                  {
                      "name":  "Startfifinder 2024.7z",
                      "url":  "https://8d2cf9429e3c19524a14a659e5a07183.r2.cloudflarestorage.com/m-auto-software/Daimler/Pack/Installer/Startfifinder%202024.7z?X-Amz-Algorithm=AWS4-HMAC-SHA256\u0026X-Amz-Credential=59cb46144927b03a7dc575be0b734ff4%2F20260428%2Fus-east-1%2Fs3%2Faws4_request\u0026X-Amz-Date=20260428T134032Z\u0026X-Amz-Expires=7200\u0026X-Amz-SignedHeaders=host\u0026x-id=GetObject\u0026X-Amz-Signature=df1746ebcbe5fbc97bb46ffeb81b2d6aaf6fa8ee693889fbf649a9ea0760f1eb"
                  },
                  {
                      "name":  "Synaptics Killer v6.zip",
                      "url":  "https://8d2cf9429e3c19524a14a659e5a07183.r2.cloudflarestorage.com/m-auto-software/Daimler/Pack/Installer/Synaptics%20Killer%20v6.zip?X-Amz-Algorithm=AWS4-HMAC-SHA256\u0026X-Amz-Credential=59cb46144927b03a7dc575be0b734ff4%2F20260428%2Fus-east-1%2Fs3%2Faws4_request\u0026X-Amz-Date=20260428T134032Z\u0026X-Amz-Expires=7200\u0026X-Amz-SignedHeaders=host\u0026x-id=GetObject\u0026X-Amz-Signature=f5a0ac83e03ce20b82587328cb555d10d338aa68576748e51a003a7c3019fc6d"
                  },
                  {
                      "name":  "vediamo 5 passthru.zip",
                      "url":  "https://8d2cf9429e3c19524a14a659e5a07183.r2.cloudflarestorage.com/m-auto-software/Daimler/Pack/Installer/vediamo%205%20passthru.zip?X-Amz-Algorithm=AWS4-HMAC-SHA256\u0026X-Amz-Credential=59cb46144927b03a7dc575be0b734ff4%2F20260428%2Fus-east-1%2Fs3%2Faws4_request\u0026X-Amz-Date=20260428T134032Z\u0026X-Amz-Expires=7200\u0026X-Amz-SignedHeaders=host\u0026x-id=GetObject\u0026X-Amz-Signature=685f5d47fa69288954b34ce85bf1b3190b99e9ae3867edc4e7fdb6028a40f506"
                  },
                  {
                      "name":  "Vediamo J2534.exe",
                      "url":  "https://8d2cf9429e3c19524a14a659e5a07183.r2.cloudflarestorage.com/m-auto-software/Daimler/Pack/Installer/Vediamo%20J2534.exe?X-Amz-Algorithm=AWS4-HMAC-SHA256\u0026X-Amz-Credential=59cb46144927b03a7dc575be0b734ff4%2F20260428%2Fus-east-1%2Fs3%2Faws4_request\u0026X-Amz-Date=20260428T134033Z\u0026X-Amz-Expires=7200\u0026X-Amz-SignedHeaders=host\u0026x-id=GetObject\u0026X-Amz-Signature=1cb354b37adb50322d7f330460939ef805199a8387fb24e09b4f8e77c912da58"
                  },
                  {
                      "name":  "wis2021.rar",
                      "url":  "https://8d2cf9429e3c19524a14a659e5a07183.r2.cloudflarestorage.com/m-auto-software/Daimler/Pack/Installer/wis2021.rar?X-Amz-Algorithm=AWS4-HMAC-SHA256\u0026X-Amz-Credential=59cb46144927b03a7dc575be0b734ff4%2F20260428%2Fus-east-1%2Fs3%2Faws4_request\u0026X-Amz-Date=20260428T134033Z\u0026X-Amz-Expires=7200\u0026X-Amz-SignedHeaders=host\u0026x-id=GetObject\u0026X-Amz-Signature=9f0e955f93d99239ecb8c28e7f0fb590f189b6edae2e7590705f69d958bb9941"
                  },
                  {
                      "name":  "WISConfigTool_7_21.rar",
                      "url":  "https://8d2cf9429e3c19524a14a659e5a07183.r2.cloudflarestorage.com/m-auto-software/Daimler/Pack/Installer/WISConfigTool_7_21.rar?X-Amz-Algorithm=AWS4-HMAC-SHA256\u0026X-Amz-Credential=59cb46144927b03a7dc575be0b734ff4%2F20260428%2Fus-east-1%2Fs3%2Faws4_request\u0026X-Amz-Date=20260428T134033Z\u0026X-Amz-Expires=7200\u0026X-Amz-SignedHeaders=host\u0026x-id=GetObject\u0026X-Amz-Signature=886ed713892c1cd809e372ed2aef6980223f8390c152a4d1c44e1f406f274732"
                  }
              ]
}